lumo/__init__.py
lumo/cli/__init__.py
lumo/cli/__main__.py
lumo/contrib/__init__.py
lumo/contrib/itertools.py
lumo/contrib/path.py
lumo/contrib/scan.py
lumo/contrib/tb.py
lumo/contrib/board/BatchEmbedding.py
lumo/contrib/board/__init__.py
lumo/contrib/data/__init__.py
lumo/contrib/data/splits.py
lumo/contrib/data/augments/__init__.py
lumo/contrib/data/augments/mix.py
lumo/contrib/data/augments/transforms.py
lumo/contrib/matplotlib/__init__.py
lumo/contrib/matplotlib/curve.py
lumo/contrib/module/__init__.py
lumo/contrib/module/ema.py
lumo/contrib/module/memoty_bank.py
lumo/contrib/nn/__init__.py
lumo/contrib/nn/functional.py
lumo/contrib/nn/loss.py
lumo/contrib/optim/__init__.py
lumo/contrib/optim/grouper.py
lumo/contrib/optim/lars.py
lumo/contrib/string/__init__.py
lumo/contrib/string/lcs.py
lumo/contrib/torch/__init__.py
lumo/contrib/torch/accuracy.py
lumo/contrib/torch/tensor.py
lumo/contrib/transforms/__init__.py
lumo/contrib/transforms/compose.py
lumo/core/__init__.py
lumo/core/attr.py
lumo/core/disk.py
lumo/core/enums.py
lumo/core/interp.py
lumo/core/list.py
lumo/core/meter.py
lumo/core/params.py
lumo/core/raises.py
lumo/core/record.py
lumo/core/tree.py
lumo/core/record_backend/__init__.py
lumo/core/record_backend/abc.py
lumo/core/record_backend/record_csv.py
lumo/core/record_backend/record_sqlite.py
lumo/core/record_backend/record_tb.py
lumo/core/record_backend/record_wandb.py
lumo/data/__init__.py
lumo/data/builder.py
lumo/data/collate.py
lumo/data/datamodule.py
lumo/data/loader.py
lumo/decorators/__init__.py
lumo/decorators/clsmethod.py
lumo/decorators/debounce.py
lumo/decorators/deprecated.py
lumo/decorators/lazy_required.py
lumo/decorators/process.py
lumo/decorators/regist.py
lumo/exp/__init__.py
lumo/exp/agent.py
lumo/exp/backup.py
lumo/exp/base.py
lumo/exp/experiment.py
lumo/exp/exphook.py
lumo/exp/lazy_panel.py
lumo/exp/metric.py
lumo/exp/watch.py
lumo/proc/__init__.py
lumo/proc/config.py
lumo/proc/date.py
lumo/proc/dependency.py
lumo/proc/dist.py
lumo-1.1.0.dist-info/LICENSE
lumo-1.1.0.dist-info/METADATA
lumo-1.1.0.dist-info/WHEEL
lumo-1.1.0.dist-info/entry_points.txt
lumo-1.1.0.dist-info/top_level.txt
lumo-1.1.0.dist-info/RECORD
